konkatenacja plusem

loch-27% javap -c StringConPlus.class

Compiled from "StringConPlus.java"
public class Lab5.StringConPlus {
  java.lang.String doneString;

  public Lab5.StringConPlus();
    Code:
       0: aload_0                           //załaduj na stos
       1: invokespecial #1                  // Method java/lang/Object."<init>":()V
       4: aload_0
       5: ldc           #7                  // String
       7: putfield      #9                  // Field doneString:Ljava/lang/String;
      10: return

  java.lang.String concatenate(java.lang.String, java.lang.String);
    Code:
       0: aload_0
       1: dup
       2: getfield      #9                  // Field doneString:Ljava/lang/String;
       5: aload_1
       6: invokedynamic #15,  0             // InvokeDynamic #0:makeConcatWithConstants:(Ljava/lang/String;Ljava/lang/String;)Ljava/lang/String;
      11: putfield      #9                  // Field doneString:Ljava/lang/String;
      14: aload_0
      15: dup
      16: getfield      #9                  // Field doneString:Ljava/lang/String;
      19: aload_2
      20: invokedynamic #15,  0             // InvokeDynamic #0:makeConcatWithConstants:(Ljava/lang/String;Ljava/lang/String;)Ljava/lang/String;
      25: putfield      #9                  // Field doneString:Ljava/lang/String;
      28: aload_0
      29: getfield      #9                  // Field doneString:Ljava/lang/String;
      32: areturn
}


konkatenacja uzywając klasy

loch-27% javap -c BuildCon.class

Compiled from "BuildCon.java"
public class Lab5.BuildCon {
  public Lab5.BuildCon();
    Code:
       0: aload_0
       1: invokespecial #1                  // Method java/lang/Object."<init>":()V
       4: return

  java.lang.String concatenate(java.lang.String, java.lang.String);
    Code:
       0: new           #7                  // class java/lang/StringBuilder
       3: dup
       4: invokespecial #9                  // Method java/lang/StringBuilder."<init>":()V
       7: astore_3
       8: aload_1
       9: aload_2
      10: invokevirtual #10                 // Method java/lang/String.concat:(Ljava/lang/String;)Ljava/lang/String;
      13: astore        4
      15: aload         4
      17: areturn
}
loch-27%






https://en.wikipedia.org/wiki/List_of_Java_bytecode_instructions